Instruction Fetch Unit/Instruction memory.v
/* 
Instruction memory takes in two inputs: A 32-bit Program counter and a 1-bit reset. 
The memory is initialized when reset is zero.
When reset is set to 1, Based on the value of PC, corresponding 32-bit Instruction code is output
*/

module Instruction_Memory (
    input [31:0] PC,
    input reset,
    output [31:0] Instruction_Code
);
    reg [7:0] Memory [35:0]; // Byte addressable memory with 36 locations

    // Under normal operation (reset = 1), we assign the instr. code, based on PC
    assign Instruction_Code = {Memory[PC+3],Memory[PC+2],Memory[PC+1],Memory[PC]};

    // Initializing memory when reset is zero
    always @(reset)
    begin
        if(reset == 0)
        begin
            // Setting 32-bit instruction: add t1, s0,s1 => 0x00940333 
            Memory[3] = 8'h00;
            Memory[2] = 8'h94;
            Memory[1] = 8'h03;
            Memory[0] = 8'h33;
            // Setting 32-bit instruction: sub t2, s2, s3 => 0x413903b3
            Memory[7] = 8'h41;
            Memory[6] = 8'h39;
            Memory[5] = 8'h03;
            Memory[4] = 8'hb3;
            // Setting 32-bit instruction: mul t0, s4, s5 => 0x035a02b3
            Memory[11] = 8'h03;
            Memory[10] = 8'h5a;
            Memory[9] = 8'h02;
            Memory[8] = 8'hb3;
            // Setting 32-bit instruction: div t3, s6, s7 => 0x037b4e33
            Memory[15] = 8'h03;
            Memory[14] = 8'h7b;
            Memory[13] = 8'h4e;
            Memory[12] = 8'h33;
        end
    end

endmodule

Instruction Fetch Unit/Instruction Fetch Unit.v
/*
The instruction fetch unit has clock and reset pins as input and 32-bit instruction code as output.
Internally the block has Instruction Memory, Program Counter(P.C) and an adder to increment counter by 4, 
on every positive clock edge.
*/

`include "Instruction memory.v"
module Instruction_Fetch_Unit(
    input clock,reset,
    output [31:0] Instruction_Code
);
reg [31:0] PC = 32'b0;  // 32-bit program counter is initialized to zero

    // Initializing the instruction memory block
    Instruction_Memory instr_mem(PC,reset,Instruction_Code);

    /*
        NOTE: Since we have only initialized 4 instructions in the memory unit,
        once P.C moves beyond 12, we will have undefined states, this can be overcome 
        by simply initializing more instructions in memory unit
    */

    always @(posedge clock, negedge reset)
    begin
        if(reset == 0)  //If reset is zero, clear the program counter
        PC <= 0;
        else
        PC<=PC+4;   // Increment program counter on positive clock edge
    end

endmodule

Instruction Fetch Unit/IFU_tb.v
`include "Instruction Fetch Unit.v"
module stimulus(

);
    reg CLOCK, RESET;
    wire [31:0] OUTPUT;

    // Initializing IFU module
    Instruction_Fetch_Unit IFU(CLOCK,RESET,OUTPUT);

    // Setting up waveform
    initial
    begin
        $dumpfile("IFU_output_wave.vcd");
        $dumpvars(0,stimulus);
    end

    // Monitoring the changes in values
    initial
    $monitor($time, "CLOCK = %b, RESET = %b, Instruction Code = %h", CLOCK,RESET,OUTPUT);

    // Initializing reset
    initial
    begin
        RESET = 1'b0;
        #20 RESET = 1'b1;
        #200 RESET = 1'b0;
        #100 RESET = 1'b1;
    end

    // Initializing clock
    initial
    begin
        CLOCK = 1;
        forever #20 CLOCK = ~CLOCK;
    end

    initial
    #400 $finish;

endmodule

Instruction Fetch Unit/IFU_output_wave.vcd
$date
	Tue Oct 13 01:45:57 2020
$end
$version
	Icarus Verilog
$end
$timescale
	1ps
$end
$scope module stimulus $end
$var wire 32 ! OUTPUT [31:0] $end
$var reg 1 " CLOCK $end
$var reg 1 # RESET $end
$scope module IFU $end
$var wire 1 " clock $end
$var wire 1 # reset $end
$var wire 32 $ Instruction_Code [31:0] $end
$var reg 32 % PC [31:0] $end
$scope module instr_mem $end
$var wire 32 & PC [31:0] $end
$var wire 1 # reset $end
$var wire 32 ' Instruction_Code [31:0] $end
$upscope $end
$upscope $end
$upscope $end
$enddefinitions $end
#0
$dumpvars
b100101000000001100110011 '
b0 &
b0 %
b100101000000001100110011 $
0#
1"
b100101000000001100110011 !
$end
#20000
0"
1#
#40000
b1000001001110010000001110110011 !
b1000001001110010000001110110011 $
b1000001001110010000001110110011 '
b100 %
b100 &
1"
#60000
0"
#80000
b11010110100000001010110011 !
b11010110100000001010110011 $
b11010110100000001010110011 '
b1000 %
b1000 &
1"
#100000
0"
#120000
b11011110110100111000110011 !
b11011110110100111000110011 $
b11011110110100111000110011 '
b1100 %
b1100 &
1"
#140000
0"
#160000
bx !
bx $
bx '
b10000 %
b10000 &
1"
#180000
0"
#200000
b10100 %
b10100 &
1"
#220000
b100101000000001100110011 !
b100101000000001100110011 $
b100101000000001100110011 '
b0 %
b0 &
0"
0#
#240000
1"
#260000
0"
#280000
1"
#300000
0"
#320000
b1000001001110010000001110110011 !
b1000001001110010000001110110011 $
b1000001001110010000001110110011 '
b100 %
b100 &
1"
1#
#340000
0"
#360000
b11010110100000001010110011 !
b11010110100000001010110011 $
b11010110100000001010110011 '
b1000 %
b1000 &
1"
#380000
0"
#400000
b11011110110100111000110011 !
b11011110110100111000110011 $
b11011110110100111000110011 '
b1100 %
b1100 &
1"
